django_modal_actions/__init__.py
django_modal_actions/apps.py
django_modal_actions/mixins.py
django_modal_actions/static/django_modal_actions/css/modal_actions.css
django_modal_actions/static/django_modal_actions/js/modal_actions.js
django_modal_actions/templates/admin/django_modal_actions/change_form.html
django_modal_actions/templates/admin/django_modal_actions/change_list.html
django_modal_actions/templates/admin/django_modal_actions/modal_actions.html
django_modal_actions/tests/__init__.py
django_modal_actions/tests/admin.py
django_modal_actions/tests/test_modal_actions.py
django_modal_actions/tests/test_settings.py
django_modal_actions/tests/urls.py
django_modal_actions-0.1.6.dist-info/licenses/LICENCE
django_modal_actions-0.1.6.dist-info/METADATA
django_modal_actions-0.1.6.dist-info/WHEEL
django_modal_actions-0.1.6.dist-info/top_level.txt
django_modal_actions-0.1.6.dist-info/RECORD
