Metadata-Version: 2.4
Name: django-modal-actions
Version: 0.1.6
Summary: A Django app for adding modal actions to the admin interface
Home-page: https://github.com/Mng-dev-ai/django-modal-actions
Author: Michael Gendy
Author-email: nagymichel13@gmail.com
License: MIT
Classifier: Environment :: Web Environment
Classifier: Framework :: Django
Classifier: Intended Audience :: Developers
Classifier: License :: OSI Approved :: MIT License
Classifier: Operating System :: OS Independent
Classifier: Programming Language :: Python
Classifier: Programming Language :: Python :: 3
Classifier: Programming Language :: Python :: 3.7
Classifier: Programming Language :: Python :: 3.8
Classifier: Programming Language :: Python :: 3.9
Classifier: Programming Language :: Python :: 3.10
Classifier: Topic :: Internet :: WWW/HTTP
Classifier: Topic :: Internet :: WWW/HTTP :: Dynamic Content
Requires-Python: >=3.7
License-File: LICENCE
Requires-Dist: Django>=3.2
Provides-Extra: dev
Requires-Dist: selenium>=4.24.0; extra == "dev"
Requires-Dist: ruff>=0.6.3; extra == "dev"
Dynamic: license-file
